setup.cfg
setup.py
python_paystack/__init__.py
python_paystack/managers.py
python_paystack/mixins.py
python_paystack/paystack_config.py
python_paystack.egg-info/PKG-INFO
python_paystack.egg-info/SOURCES.txt
python_paystack.egg-info/dependency_links.txt
python_paystack.egg-info/requires.txt
python_paystack.egg-info/top_level.txt