Metadata-Version: 1.0
Name: python-paystack
Version: 1.0.9
Summary: A Paystack API wrapper
Home-page: UNKNOWN
Author: Nwalor Chibuzor
Author-email: nwalorc@gmail.com
License: MIT
Platform: UNKNOWN
